{
  "abbrevs": [
        "AED",
        "AFN",
        "ALL",
        "AMD",
        "ANG",
        "AOA",
        "ARS",
        "AUD",
        "AWG",
        "AZN",
        "BAM",
        "BBD",
        "BDT",
        "BEF",
        "BGN",
        "BHD",
        "BIF",
        "BMD",
        "BND",
        "BOB",
        "BRL",
        "BSD",
        "BTC",
        "BTN",
        "BWP",
        "BYR",
        "BZD",
        "CAD",
        "CDF",
        "CHF",
        "CLP",
        "CNY",
        "COP",
        "CRC",
        "CUC",
        "CUP",
        "CVE",
        "CZK",
        "DEM",
        "DJF",
        "DKK",
        "DOP",
        "DZD",
        "EEK",
        "EGP",
        "ERN",
        "ETB",
        "EUR",
        "FJD",
        "FKP",
        "GBP",
        "GEL",
        "GGP",
        "GHS",
        "GIP",
        "GMD",
        "GNF",
        "GRD",
        "GTQ",
        "GYD",
        "HKD",
        "HNL",
        "HRK",
        "HTG",
        "HUF",
        "IDR",
        "ILS",
        "IMP",
        "INR",
        "IQD",
        "IRR",
        "ISK",
        "ITL",
        "JEP",
        "JMD",
        "JOD",
        "JPY",
        "KES",
        "KGS",
        "KHR",
        "KMF",
        "KPW",
        "KRW",
        "KWD",
        "KYD",
        "KZT",
        "LAK",
        "LBP",
        "LKR",
        "LRD",
        "LSL",
        "LTL",
        "LVL",
        "LYD",
        "MAD",
        "MDL",
        "MGA",
        "MKD",
        "MMK",
        "MNT",
        "MOP",
        "MRU",
        "MUR",
        "MVR",
        "MWK",
        "MXN",
        "MYR",
        "MZM",
        "MZN",
        "NAD",
        "NGN",
        "NIO",
        "NOK",
        "NPR",
        "NZD",
        "OMR",
        "PAB",
        "PEN",
        "PGK",
        "PHP",
        "PKR",
        "PLN",
        "PYG",
        "QAR",
        "RON",
        "RSD",
        "RUB",
        "RWF",
        "SAR",
        "SBD",
        "SCR",
        "SDG",
        "SEK",
        "SGD",
        "SHP",
        "SKK",
        "SLL",
        "SOS",
        "SRD",
        "STD",
        "SVC",
        "SYP",
        "SZL",
        "THB",
        "TJS",
        "TMT",
        "TND",
        "TRY",
        "TTD",
        "TVD",
        "TWD",
        "TZS",
        "UAH",
        "UGX",
        "USD",
        "UYU",
        "UZS",
        "VEB",
        "VEF",
        "VND",
        "VUV",
        "WST",
        "XAF",
        "XCD",
        "XDR",
        "XOF",
        "XPF",
        "YER",
        "ZAR",
        "ZMK",
        "ZWD",
        "ZWR"
    ],
    "currencies": {
        "afghani": [
            [
                "AFN",
                true
            ]
        ],
        "baht": [
            [
                "THB",
                true
            ]
        ],
        "balboa": [
            [
                "PAB",
                true
            ]
        ],
        "bitcoin": [
            [
                "BTC",
                true
            ]
        ],
        "bolivar": [
            [
                "VEF",
                true
            ]
        ],
        "bolã­viano": [
            [
                "BOB",
                true
            ]
        ],
        "bucks": [
            [
                "AUD",
                false
            ],
            [
                "BBD",
                false
            ],
            [
                "BMD",
                false
            ],
            [
                "BND",
                false
            ],
            [
                "BSD",
                false
            ],
            [
                "BZD",
                false
            ],
            [
                "CAD",
                false
            ],
            [
                "FJD",
                false
            ],
            [
                "GYD",
                false
            ],
            [
                "HKD",
                false
            ],
            [
                "JMD",
                false
            ],
            [
                "KYD",
                false
            ],
            [
                "LRD",
                false
            ],
            [
                "NAD",
                false
            ],
            [
                "NZD",
                false
            ],
            [
                "SBD",
                false
            ],
            [
                "SGD",
                false
            ],
            [
                "SRD",
                false
            ],
            [
                "TTD",
                false
            ],
            [
                "TVD",
                false
            ],
            [
                "TWD",
                false
            ],
            [
                "USD",
                true
            ],
            [
                "XCD",
                false
            ],
            [
                "ZWD",
                false
            ]
        ],
        "cedi": [
            [
                "GHS",
                true
            ]
        ],
        "colon": [
            [
                "CRC",
                true
            ],
            [
                "SVC",
                false
            ]
        ],
        "cordoba": [
            [
                "NIO",
                true
            ]
        ],
        "denar": [
            [
                "MKD",
                true
            ]
        ],
        "dinar": [
            [
                "RSD",
                true
            ]
        ],
        "dollar": [
            [
                "AUD",
                false
            ],
            [
                "BBD",
                false
            ],
            [
                "BMD",
                false
            ],
            [
                "BND",
                false
            ],
            [
                "BSD",
                false
            ],
            [
                "BZD",
                false
            ],
            [
                "CAD",
                false
            ],
            [
                "FJD",
                false
            ],
            [
                "GYD",
                false
            ],
            [
                "HKD",
                false
            ],
            [
                "JMD",
                false
            ],
            [
                "KYD",
                false
            ],
            [
                "LRD",
                false
            ],
            [
                "NAD",
                false
            ],
            [
                "NZD",
                false
            ],
            [
                "SBD",
                false
            ],
            [
                "SGD",
                false
            ],
            [
                "SRD",
                false
            ],
            [
                "TTD",
                false
            ],
            [
                "TVD",
                false
            ],
            [
                "TWD",
                false
            ],
            [
                "USD",
                true
            ],
            [
                "XCD",
                false
            ],
            [
                "ZWD",
                false
            ]
        ],
        "dong": [
            [
                "VND",
                true
            ]
        ],
        "euro": [
            [
                "EUR",
                true
            ]
        ],
        "forint": [
            [
                "HUF",
                true
            ]
        ],
        "franc": [
            [
                "CHF",
                true
            ]
        ],
        "guarani": [
            [
                "PYG",
                true
            ]
        ],
        "guilder": [
            [
                "ANG",
                true
            ],
            [
                "AWG",
                false
            ]
        ],
        "hryvnia": [
            [
                "UAH",
                true
            ]
        ],
        "kip": [
            [
                "LAK",
                true
            ]
        ],
        "koruna": [
            [
                "CZK",
                true
            ]
        ],
        "krona": [
            [
                "ISK",
                false
            ],
            [
                "SEK",
                true
            ]
        ],
        "krone": [
            [
                "DKK",
                true
            ],
            [
                "NOK",
                false
            ]
        ],
        "kuna": [
            [
                "HRK",
                true
            ]
        ],
        "lek": [
            [
                "ALL",
                true
            ]
        ],
        "lempira": [
            [
                "HNL",
                true
            ]
        ],
        "leu": [
            [
                "RON",
                true
            ]
        ],
        "lev": [
            [
                "BGN",
                true
            ]
        ],
        "manat": [
            [
                "AZN",
                true
            ]
        ],
        "marka": [
            [
                "BAM",
                true
            ]
        ],
        "metical": [
            [
                "MZN",
                true
            ]
        ],
        "naira": [
            [
                "NGN",
                true
            ]
        ],
        "peso": [
            [
                "ARS",
                false
            ],
            [
                "CLP",
                false
            ],
            [
                "COP",
                false
            ],
            [
                "CUP",
                false
            ],
            [
                "DOP",
                false
            ],
            [
                "MXN",
                true
            ],
            [
                "PHP",
                false
            ],
            [
                "UYU",
                false
            ]
        ],
        "pound": [
            [
                "EGP",
                false
            ],
            [
                "FKP",
                false
            ],
            [
                "GBP",
                true
            ],
            [
                "GGP",
                false
            ],
            [
                "GIP",
                false
            ],
            [
                "IMP",
                false
            ],
            [
                "JEP",
                false
            ],
            [
                "LBP",
                false
            ],
            [
                "SHP",
                false
            ],
            [
                "SYP",
                false
            ]
        ],
        "pula": [
            [
                "BWP",
                true
            ]
        ],
        "quetzal": [
            [
                "GTQ",
                true
            ]
        ],
        "rand": [
            [
                "ZAR",
                true
            ]
        ],
        "real": [
            [
                "BRL",
                true
            ]
        ],
        "renminbi": [
            [
                "CNY",
                true
            ]
        ],
        "rial": [
            [
                "IRR",
                true
            ],
            [
                "OMR",
                false
            ],
            [
                "YER",
                false
            ]
        ],
        "riel": [
            [
                "KHR",
                true
            ]
        ],
        "ringgit": [
            [
                "MYR",
                true
            ]
        ],
        "riyal": [
            [
                "QAR",
                false
            ],
            [
                "SAR",
                true
            ]
        ],
        "ruble": [
            [
                "BYR",
                false
            ],
            [
                "RUB",
                true
            ]
        ],
        "rupee": [
            [
                "LKR",
                false
            ],
            [
                "MUR",
                false
            ],
            [
                "NPR",
                false
            ],
            [
                "PKR",
                true
            ],
            [
                "SCR",
                false
            ]
        ],
        "rupiah": [
            [
                "IDR",
                true
            ]
        ],
        "shekel": [
            [
                "ILS",
                true
            ]
        ],
        "shilling": [
            [
                "SOS",
                true
            ]
        ],
        "sol": [
            [
                "PEN",
                true
            ]
        ],
        "som": [
            [
                "KGS",
                true
            ],
            [
                "UZS",
                false
            ]
        ],
        "tenge": [
            [
                "KZT",
                true
            ]
        ],
        "tughrik": [
            [
                "MNT",
                true
            ]
        ],
        "won": [
            [
                "KPW",
                false
            ],
            [
                "KRW",
                true
            ]
        ],
        "yen": [
            [
                "JPY",
                true
            ]
        ],
        "zloty": [
            [
                "PLN",
                true
            ]
        ]
    },
    "keywords": {
        "Afghan": "AFN",
        "Afghanistan": "AFN",
        "Albania": "ALL",
        "Albanian": "ALL",
        "Algerian": "DZD",
        "Angolan": "AOA",
        "Argentina": "ARS",
        "Argentine": "ARS",
        "Armenian": "AMD",
        "Aruba": "AWG",
        "Aruban": "AWG",
        "Australia": "AUD",
        "Australian": "AUD",
        "Azerbaijan New": "AZN",
        "Azerbaijani": "AZN",
        "Bahamas": "BSD",
        "Bahamian": "BSD",
        "Bahraini": "BHD",
        "Bangladeshi": "BDT",
        "Barbadian": "BBD",
        "Barbados": "BBD",
        "Belarus": "BYR",
        "Belarusian": "BYR",
        "Belgian": "BEF",
        "Belize": "BZD",
        "Bermuda": "BMD",
        "Bermudan": "BMD",
        "Bermudian": "BMD",
        "Bhutanese": "BTN",
        "Bolivia": "BOB",
        "Bolivian": "BOB",
        "Bosnia and Herzegovina Convertible": "BAM",
        "Bosnia and Herzegovina konvertibilna": "BAM",
        "Bosnia-Herzegovina Convertible": "BAM",
        "Botswana": "BWP",
        "Botswanan": "BWP",
        "Brazil": "BRL",
        "Brazilian": "BRL",
        "British": "GBP",
        "Brunei": "BND",
        "Brunei Darussalam": "BND",
        "Bulgaria": "BGN",
        "Bulgarian": "BGN",
        "Burundi": "BIF",
        "Burundian": "BIF",
        "Cambodia": "KHR",
        "Cambodian": "KHR",
        "Canada": "CAD",
        "Canadian": "CAD",
        "Cape Verdean": "CVE",
        "Cayman Islands": "KYD",
        "Central African CFA": "XAF",
        "CFP": "XPF",
        "Chile": "CLP",
        "Chilean": "CLP",
        "China Yuan": "CNY",
        "Chinese": "CNY",
        "Chinese/Yuan": "CNY",
        "Colombia": "COP",
        "Colombian": "COP",
        "Comorian": "KMF",
        "Congolese": "CDF",
        "Costa Rica": "CRC",
        "Costa Rican": "CRC",
        "Croatia": "HRK",
        "Croatian": "HRK",
        "Cuba": "CUP",
        "Cuban": "CUC",
        "Cuban Convertible": "CUC",
        "Czech": "CZK",
        "Czech Republic": "CZK",
        "Danish": "DKK",
        "Denmark": "DKK",
        "Djiboutian": "DJF",
        "Dominican": "DOP",
        "Dominican Republic": "DOP",
        "East Caribbean": "XCD",
        "Egypt": "EGP",
        "Egyptian": "EGP",
        "El Salvador": "SVC",
        "Eritrean": "ERN",
        "Estonian": "EEK",
        "Ethiopian": "ETB",
        "Euro Member": "EUR",
        "European": "EUR",
        "Falkland Islands": "FKP",
        "Falkland Islands ": "FKP",
        "Fiji": "FJD",
        "Fijian": "FJD",
        "Gambian": "GMD",
        "Georgian": "GEL",
        "German": "DEM",
        "Ghana": "GHS",
        "Ghanaian": "GHS",
        "Gibraltar": "GIP",
        "Greek": "GRD",
        "Guatemala": "GTQ",
        "Guatemalan": "GTQ",
        "Guernsey": "GGP",
        "Guinean": "GNF",
        "Guyana": "GYD",
        "Guyanaese": "GYD",
        "Guyanese": "GYD",
        "Haitian": "HTG",
        "Honduran": "HNL",
        "Honduras": "HNL",
        "Hong Kong": "HKD",
        "Hungarian": "HUF",
        "Hungary": "HUF",
        "Iceland": "ISK",
        "Icelandic": "ISK",
        "Indian": "INR",
        "Indonesia": "IDR",
        "Indonesian": "IDR",
        "Iran": "IRR",
        "Iranian": "IRR",
        "Iraqi": "IQD",
        "Isle of Man": "IMP",
        "Israel": "ILS",
        "Israeli New": "ILS",
        "Israeli new": "ILS",
        "Italian": "ITL",
        "Jamaica": "JMD",
        "Jamaican": "JMD",
        "Japan": "JPY",
        "Japanese": "JPY",
        "Jersey": "JEP",
        "Jordanian": "JOD",
        "Kazakhstan": "KZT",
        "Kazakhstani": "KZT",
        "Kenyan": "KES",
        "Korea ": "KRW",
        "Kuwaiti": "KWD",
        "Kyrgystani": "KGS",
        "Kyrgyzstan": "KGS",
        "Kyrgyzstani": "KGS",
        "Lao": "LAK",
        "Laos": "LAK",
        "Laotian": "LAK",
        "Latvian": "LVL",
        "Lebanese": "LBP",
        "Lebanon": "LBP",
        "Lesotho": "LSL",
        "Liberia": "LRD",
        "Liberian": "LRD",
        "Libyan": "LYD",
        "Lithuanian": "LTL",
        "Macanese": "MOP",
        "Macedonia": "MKD",
        "Macedonian": "MKD",
        "Malagasy": "MGA",
        "Malawian": "MWK",
        "Malaysia": "MYR",
        "Malaysian": "MYR",
        "Maldivian": "MVR",
        "Mauritanian": "MRU",
        "Mauritian": "MUR",
        "Mauritius": "MUR",
        "Mexican": "MXN",
        "Mexico": "MXN",
        "Moldovan": "MDL",
        "Mongolia": "MNT",
        "Mongolian": "MNT",
        "Moroccan": "MAD",
        "Mozambican": "MZM",
        "Mozambique": "MZN",
        "Myanma": "MMK",
        "Myanmar": "MMK",
        "Namibia": "NAD",
        "Namibian": "NAD",
        "Nepal": "NPR",
        "Nepalese": "NPR",
        "Netherlands Antillean": "ANG",
        "Netherlands Antilles": "ANG",
        "New Taiwan": "TWD",
        "New Zealand": "NZD",
        "Nicaragua": "NIO",
        "Nicaraguan": "NIO",
        "Nigeria": "NGN",
        "Nigerian": "NGN",
        "North Korean": "KPW",
        "Norway": "NOK",
        "Norwegian": "NOK",
        "Oman": "OMR",
        "Omani": "OMR",
        "Pakistan": "PKR",
        "Pakistani": "PKR",
        "Panama": "PAB",
        "Panamanian": "PAB",
        "Papua New Guinean": "PGK",
        "Paraguay": "PYG",
        "Paraguayan": "PYG",
        "Peru": "PEN",
        "Peruvian nuevo": "PEN",
        "Peruvian Nuevo": "PEN",
        "Philippine": "PHP",
        "Philippines": "PHP",
        "Poland": "PLN",
        "Polish": "PLN",
        "Qatar": "QAR",
        "Qatari": "QAR",
        "Romania New": "RON",
        "Romanian": "RON",
        "Russia": "RUB",
        "Russian": "RUB",
        "Rwandan": "RWF",
        "Saint Helena": "SHP",
        "Salvadoran": "SVC",
        "Samoan": "WST",
        "Saudi": "SAR",
        "Saudi Arabia": "SAR",
        "Serbia": "RSD",
        "Serbian": "RSD",
        "Seychelles": "SCR",
        "Seychellois": "SCR",
        "Sierra Leonean": "SLL",
        "Singapore": "SGD",
        "Slovak": "SKK",
        "Solomon Islands": "SBD",
        "Somali": "SOS",
        "Somalia": "SOS",
        "South Africa": "ZAR",
        "South African": "ZAR",
        "South Korean": "KRW",
        "Special Drawing": "XDR",
        "Sri Lanka": "LKR",
        "Sri Lankan": "LKR",
        "St. Helena": "SHP",
        "Sudanese": "SDG",
        "Suriname": "SRD",
        "Surinamese": "SRD",
        "Swazi": "SZL",
        "Sweden": "SEK",
        "Swedish": "SEK",
        "Swiss": "CHF",
        "Switzerland": "CHF",
        "Syria": "SYP",
        "Syrian": "SYP",
        "São Tomé & Príncipe": "STD",
        "Taiwan New": "TWD",
        "Tajikistani": "TJS",
        "Tanzanian": "TZS",
        "Thai": "THB",
        "Thailand": "THB",
        "Trinidad & Tobago": "TTD",
        "Trinidad and Tobago": "TTD",
        "Tunisian": "TND",
        "Turkish": "TRY",
        "Turkish new": "TRY",
        "Turkmen": "TMT",
        "Turkmenistani": "TMT",
        "Tuvalu": "TVD",
        "UAE": "AED",
        "Ugandan": "UGX",
        "Ukraine": "UAH",
        "Ukrainian": "UAH",
        "United Arab Emirates": "AED",
        "United Kingdom": "GBP",
        "United States": "USD",
        "Uruguay": "UYU",
        "Uruguayan": "UYU",
        "US": "USD",
        "Uzbekistan": "UZS",
        "Uzbekistani": "UZS",
        "Vanuatu": "VUV",
        "Venezuela": "VEF",
        "Venezuelan": "VEB",
        "Viet Nam": "VND",
        "Vietnamese": "VND",
        "West African CFA": "XOF",
        "Yemen": "YER",
        "Yemeni": "YER",
        "Zambian": "ZMK",
        "Zimbabwe": "ZWD",
        "Zimbabwean": "ZWR"
    },
    "symbols": {
        "$": [
            [
                "ARS",
                false
            ],
            [
                "AUD",
                false
            ],
            [
                "BBD",
                false
            ],
            [
                "BMD",
                false
            ],
            [
                "BND",
                false
            ],
            [
                "BSD",
                false
            ],
            [
                "CAD",
                false
            ],
            [
                "CLP",
                false
            ],
            [
                "COP",
                false
            ],
            [
                "FJD",
                false
            ],
            [
                "GYD",
                false
            ],
            [
                "HKD",
                false
            ],
            [
                "KYD",
                false
            ],
            [
                "LRD",
                false
            ],
            [
                "MXN",
                false
            ],
            [
                "NAD",
                false
            ],
            [
                "NZD",
                false
            ],
            [
                "SBD",
                false
            ],
            [
                "SGD",
                false
            ],
            [
                "SRD",
                false
            ],
            [
                "SVC",
                false
            ],
            [
                "TVD",
                false
            ],
            [
                "USD",
                true
            ],
            [
                "XCD",
                false
            ]
        ],
        "$A": [
            [
                "AUD",
                true
            ]
        ],
        "$b": [
            [
                "BOB",
                true
            ]
        ],
        "$B": [
            [
                "BOB",
                true
            ]
        ],
        "$U": [
            [
                "UYU",
                true
            ]
        ],
        "$US": [
            [
                "USD",
                true
            ]
        ],
        ".د.ب": [
            [
                "BHD",
                true
            ]
        ],
        "Afs": [
            [
                "AFN",
                true
            ]
        ],
        "AFS": [
            [
                "AFN",
                true
            ]
        ],
        "AMD": [
            [
                "AMD",
                true
            ]
        ],
        "AZN": [
            [
                "AZN",
                true
            ]
        ],
        "B./": [
            [
                "PAB",
                true
            ]
        ],
        "B/.": [
            [
                "PAB",
                true
            ]
        ],
        "BD$": [
            [
                "BMD",
                true
            ]
        ],
        "BDS$": [
            [
                "BBD",
                true
            ]
        ],
        "Bds$": [
            [
                "BBD",
                true
            ]
        ],
        "BGN": [
            [
                "BGN",
                true
            ]
        ],
        "BR": [
            [
                "BYR",
                true
            ]
        ],
        "Br": [
            [
                "BYR",
                true
            ]
        ],
        "BS": [
            [
                "VEF",
                true
            ]
        ],
        "Bs": [
            [
                "VEF",
                true
            ]
        ],
        "Bs.": [
            [
                "BOB",
                true
            ]
        ],
        "BS.": [
            [
                "BOB",
                true
            ]
        ],
        "BZ$": [
            [
                "BZD",
                true
            ]
        ],
        "C$": [
            [
                "NIO",
                true
            ]
        ],
        "CHF": [
            [
                "CHF",
                true
            ]
        ],
        "Col$": [
            [
                "COP",
                true
            ]
        ],
        "COL$": [
            [
                "COP",
                true
            ]
        ],
        "DIN.": [
            [
                "RSD",
                true
            ]
        ],
        "din.": [
            [
                "RSD",
                true
            ]
        ],
        "DT": [
            [
                "TND",
                true
            ]
        ],
        "EC$": [
            [
                "XCD",
                true
            ]
        ],
        "ESC": [
            [
                "CVE",
                true
            ]
        ],
        "Esc": [
            [
                "CVE",
                true
            ]
        ],
        "FBU": [
            [
                "BIF",
                true
            ]
        ],
        "FBu": [
            [
                "BIF",
                true
            ]
        ],
        "Fdj": [
            [
                "DJF",
                true
            ]
        ],
        "FDJ": [
            [
                "DJF",
                true
            ]
        ],
        "FG": [
            [
                "GNF",
                true
            ]
        ],
        "FJ$": [
            [
                "FJD",
                true
            ]
        ],
        "FMG": [
            [
                "MGA",
                true
            ]
        ],
        "Fr.": [
            [
                "CHF",
                true
            ]
        ],
        "FR.": [
            [
                "CHF",
                true
            ]
        ],
        "Ft": [
            [
                "HUF",
                true
            ]
        ],
        "FT": [
            [
                "HUF",
                true
            ]
        ],
        "GEL": [
            [
                "GEL",
                true
            ]
        ],
        "GH₵": [
            [
                "GHS",
                true
            ]
        ],
        "GS": [
            [
                "PYG",
                true
            ]
        ],
        "Gs": [
            [
                "PYG",
                true
            ]
        ],
        "GY$": [
            [
                "GYD",
                true
            ]
        ],
        "HK$": [
            [
                "HKD",
                true
            ]
        ],
        "IRR": [
            [
                "IRR",
                true
            ]
        ],
        "J$": [
            [
                "JMD",
                true
            ]
        ],
        "JOD": [
            [
                "JOD",
                true
            ]
        ],
        "KM": [
            [
                "BAM",
                true
            ]
        ],
        "KMF": [
            [
                "KMF",
                true
            ]
        ],
        "kn": [
            [
                "HRK",
                true
            ]
        ],
        "KN": [
            [
                "LAK",
                true
            ]
        ],
        "kr": [
            [
                "DKK",
                false
            ],
            [
                "ISK",
                false
            ],
            [
                "NOK",
                false
            ],
            [
                "SEK",
                true
            ]
        ],
        "KR": [
            [
                "EEK",
                true
            ]
        ],
        "Kr": [
            [
                "DKK",
                true
            ]
        ],
        "KSH": [
            [
                "KES",
                true
            ]
        ],
        "KSh": [
            [
                "KES",
                true
            ]
        ],
        "KWD": [
            [
                "KWD",
                true
            ]
        ],
        "KY$": [
            [
                "KYD",
                true
            ]
        ],
        "Kz": [
            [
                "AOA",
                true
            ]
        ],
        "KZ": [
            [
                "AOA",
                true
            ]
        ],
        "KČ": [
            [
                "CZK",
                true
            ]
        ],
        "Kč": [
            [
                "CZK",
                true
            ]
        ],
        "L$": [
            [
                "LRD",
                true
            ]
        ],
        "LD": [
            [
                "LYD",
                true
            ]
        ],
        "Le": [
            [
                "SLL",
                true
            ]
        ],
        "LE": [
            [
                "SLL",
                true
            ]
        ],
        "lei": [
            [
                "RON",
                true
            ]
        ],
        "LEI": [
            [
                "RON",
                true
            ]
        ],
        "Lek": [
            [
                "ALL",
                true
            ]
        ],
        "LEK": [
            [
                "ALL",
                true
            ]
        ],
        "LS": [
            [
                "SYP",
                true
            ]
        ],
        "Ls": [
            [
                "LVL",
                true
            ]
        ],
        "LT": [
            [
                "LTL",
                true
            ]
        ],
        "Lt": [
            [
                "LTL",
                true
            ]
        ],
        "MAD": [
            [
                "MAD",
                true
            ]
        ],
        "MDL": [
            [
                "MDL",
                true
            ]
        ],
        "MK": [
            [
                "MWK",
                true
            ]
        ],
        "MKD": [
            [
                "MKD",
                true
            ]
        ],
        "MT": [
            [
                "MZN",
                true
            ]
        ],
        "MTn": [
            [
                "MZM",
                true
            ]
        ],
        "MTN": [
            [
                "MZM",
                true
            ]
        ],
        "N$": [
            [
                "NAD",
                true
            ]
        ],
        "NAƑ": [
            [
                "ANG",
                true
            ]
        ],
        "NAƒ": [
            [
                "ANG",
                true
            ]
        ],
        "NFA": [
            [
                "ERN",
                true
            ]
        ],
        "Nfa": [
            [
                "ERN",
                true
            ]
        ],
        "NRS": [
            [
                "NPR",
                true
            ]
        ],
        "NRs": [
            [
                "NPR",
                true
            ]
        ],
        "NT$": [
            [
                "TWD",
                true
            ]
        ],
        "Nu.": [
            [
                "BTN",
                true
            ]
        ],
        "NU.": [
            [
                "BTN",
                true
            ]
        ],
        "NZ$": [
            [
                "NZD",
                true
            ]
        ],
        "OMR": [
            [
                "OMR",
                true
            ]
        ],
        "p.": [
            [
                "BYR",
                true
            ]
        ],
        "P.": [
            [
                "BYR",
                true
            ]
        ],
        "QR": [
            [
                "QAR",
                true
            ]
        ],
        "R$": [
            [
                "BRL",
                true
            ]
        ],
        "RD$": [
            [
                "DOP",
                true
            ]
        ],
        "Rf": [
            [
                "MVR",
                true
            ]
        ],
        "RF": [
            [
                "MVR",
                true
            ]
        ],
        "RM": [
            [
                "MYR",
                true
            ]
        ],
        "Rp": [
            [
                "IDR",
                true
            ]
        ],
        "RP": [
            [
                "IDR",
                true
            ]
        ],
        "RS.": [
            [
                "PKR",
                true
            ]
        ],
        "Rs.": [
            [
                "PKR",
                true
            ]
        ],
        "S$": [
            [
                "SGD",
                true
            ]
        ],
        "S/.": [
            [
                "PEN",
                true
            ]
        ],
        "SDG": [
            [
                "SDG",
                true
            ]
        ],
        "SDR": [
            [
                "XDR",
                true
            ]
        ],
        "Sh.": [
            [
                "SOS",
                true
            ]
        ],
        "SH.": [
            [
                "SOS",
                true
            ]
        ],
        "SI$": [
            [
                "SBD",
                true
            ]
        ],
        "SR": [
            [
                "SAR",
                true
            ]
        ],
        "TJS": [
            [
                "TJS",
                true
            ]
        ],
        "TRY": [
            [
                "TRY",
                true
            ]
        ],
        "TT$": [
            [
                "TTD",
                true
            ]
        ],
        "TZS": [
            [
                "TZS",
                true
            ]
        ],
        "UAH": [
            [
                "UAH",
                true
            ]
        ],
        "UM": [
            [
                "MRU",
                true
            ]
        ],
        "US$": [
            [
                "USD",
                true
            ]
        ],
        "USh": [
            [
                "UGX",
                true
            ]
        ],
        "USH": [
            [
                "UGX",
                true
            ]
        ],
        "UZS": [
            [
                "UZS",
                true
            ]
        ],
        "VT": [
            [
                "VUV",
                true
            ]
        ],
        "WS$": [
            [
                "WST",
                true
            ]
        ],
        "YER": [
            [
                "YER",
                true
            ]
        ],
        "Z$": [
            [
                "ZWD",
                true
            ]
        ],
        "ZK": [
            [
                "ZMK",
                true
            ]
        ],
        "ZŁ": [
            [
                "PLN",
                true
            ]
        ],
        "zł": [
            [
                "PLN",
                true
            ]
        ],
        "¢": [
            [
                "GHS",
                true
            ]
        ],
        "£": [
            [
                "EGP",
                false
            ],
            [
                "FKP",
                false
            ],
            [
                "GBP",
                true
            ],
            [
                "GGP",
                false
            ],
            [
                "GIP",
                false
            ],
            [
                "IMP",
                false
            ],
            [
                "JEP",
                false
            ],
            [
                "LBP",
                false
            ],
            [
                "SHP",
                false
            ],
            [
                "SYP",
                false
            ]
        ],
        "¥": [
            [
                "CNY",
                true
            ],
            [
                "JPY",
                false
            ]
        ],
        "Ƀ": [
            [
                "BTC",
                true
            ]
        ],
        "Ƒ": [
            [
                "ANG",
                true
            ],
            [
                "AWG",
                false
            ]
        ],
        "ƒ": [
            [
                "ANG",
                true
            ],
            [
                "AWG",
                false
            ]
        ],
        "ден": [
            [
                "MKD",
                true
            ]
        ],
        "ДЕН": [
            [
                "MKD",
                true
            ]
        ],
        "Дин.": [
            [
                "RSD",
                true
            ]
        ],
        "ДИН.": [
            [
                "RSD",
                true
            ]
        ],
        "лв": [
            [
                "BGN",
                false
            ],
            [
                "KGS",
                true
            ],
            [
                "KZT",
                false
            ],
            [
                "UZS",
                false
            ]
        ],
        "ЛВ": [
            [
                "BGN",
                false
            ],
            [
                "KGS",
                true
            ],
            [
                "KZT",
                false
            ],
            [
                "UZS",
                false
            ]
        ],
        "МАН": [
            [
                "AZN",
                true
            ]
        ],
        "ман": [
            [
                "AZN",
                true
            ]
        ],
        "руб": [
            [
                "RUB",
                true
            ]
        ],
        "РУБ": [
            [
                "RUB",
                true
            ]
        ],
        "сом": [
            [
                "KGS",
                true
            ]
        ],
        "СОМ": [
            [
                "KGS",
                true
            ]
        ],
        "؋": [
            [
                "AFN",
                true
            ]
        ],
        "د.إ;": [
            [
                "AED",
                true
            ]
        ],
        "د.ج": [
            [
                "DZD",
                true
            ]
        ],
        "د.ع": [
            [
                "IQD",
                true
            ]
        ],
        "৳": [
            [
                "BDT",
                true
            ]
        ],
        "฿": [
            [
                "THB",
                true
            ]
        ],
        "៛": [
            [
                "KHR",
                true
            ]
        ],
        "₡": [
            [
                "CRC",
                true
            ]
        ],
        "₦": [
            [
                "NGN",
                true
            ]
        ],
        "₨": [
            [
                "LKR",
                false
            ],
            [
                "MUR",
                false
            ],
            [
                "NPR",
                false
            ],
            [
                "PKR",
                true
            ],
            [
                "SCR",
                false
            ]
        ],
        "₩": [
            [
                "KPW",
                false
            ],
            [
                "KRW",
                true
            ]
        ],
        "₪": [
            [
                "ILS",
                true
            ]
        ],
        "₫": [
            [
                "VND",
                true
            ]
        ],
        "€": [
            [
                "EUR",
                true
            ]
        ],
        "₭": [
            [
                "LAK",
                true
            ]
        ],
        "₮": [
            [
                "MNT",
                true
            ]
        ],
        "₱": [
            [
                "CUP",
                false
            ],
            [
                "PHP",
                true
            ]
        ],
        "₲": [
            [
                "PYG",
                true
            ]
        ],
        "₴": [
            [
                "UAH",
                true
            ]
        ],
        "₹": [
            [
                "INR",
                true
            ]
        ],
        "﷼": [
            [
                "IRR",
                true
            ],
            [
                "OMR",
                false
            ],
            [
                "QAR",
                false
            ],
            [
                "SAR",
                false
            ],
            [
                "YER",
                false
            ]
        ]
    },
    "units": {
        "one": 1,
        "two": 2,
        "three": 3,
        "four": 4,
        "five": 5,
        "six": 6,
        "seven": 7,
        "eight": 8,
        "nine": 9,
        "ten": 10,
        "eleven": 11,
        "twelve": 12,
        "thirteen": 13,
        "fourteen": 14,
        "fifteen": 15,
        "sixteen": 16,
        "seventeen": 17,
        "eighteen": 18,
        "nineteen": 19,
        "twenty": 20,
        "thirty": 30,
        "fourty": 40,
        "fifty": 50,
        "sixty": 60,
        "seventy": 70,
        "eighty": 80,
        "ninety": 90,
        "hundred": 100,
        "thousand": 1000,
        "million": 1000000,
        "billion": 1000000000,
        "trillion": 1000000000000,
        "cent": 0.01,
        "k": 1000,
        "m": 1000000,
        "mil": 1000000,
        "mn": 1000000,
        "b": 1000000000,
        "bn": 1000000000
    }
}